{"PrimaryDetails":{"AssetTitle":"sagi_051","AssetURL":"https://qa.chrysalis.microsoft.com/assets/add","AssetType":"IP Component","Description":"{\"blocks\":[{\"key\":\"b1jam\",\"text\":\"provideing project , teams  dashboard url\",\"type\":\"unstyled\",\"depth\":0,\"inlineStyleRanges\":[],\"entityRanges\":[],\"data\":{}},{\"key\":\"5g57i\",\"text\":\"\",\"type\":\"unstyled\",\"depth\":0,\"inlineStyleRanges\":[],\"entityRanges\":[],\"data\":{}}],\"entityMap\":{}}","Products":[],"Scenarios":[],"SolutionAreas":[],"Tags":["QATESTING"],"AssetVersion":"sagi","AssetContributors":[],"AssetOwner":["v-saginaveen@microsoft.com"],"RegisteredBy":"v-saginaveen@microsoft.com","RegisteredDate":"2023-01-14T08:55:58.1476067Z","IsPrivate":false,"PrivateUsers":[],"EffortsSpentWithoutAsset":null,"EffortsSpentWithAsset":null,"LinkedAssets":[],"AssetURLScope":"MS-FTE","AssetURLAccessSteps":"","DeliveryProductID":"","DomainServiceline":null},"IPDetails":{"DisplayVersion":"sagi","WorkItems":[],"Repository":[],"AssociatedComponents":[],"Pipelines":[],"docsAsCode":[],"iterationAreaTeams":[],"Queries":[],"Dashboards":[{"name":"Project","sourceType":"ADO","url":"https://dev.azure.com/chrysalis-innersource/IBIS%20(Intelligent%20Bootstrap%20Integrated%20System)/_dashboards/dashboard/0b085c9c-afe2-4636-a389-35d0218c3dd9","teamName":""},{"name":"PraleshTestDashboard","sourceType":"ADO","url":"https://dev.azure.com/chrysalis-innersource/IBIS%20(Intelligent%20Bootstrap%20Integrated%20System)/_dashboards/dashboard/cdfb7d1b-db30-4f28-b779-33d74934975d","teamName":"IBIS (Intelligent Bootstrap Integrated System) Team"}],"VariableGroups":[],"PreProcessingSteps":"","PostProcessingSteps":""}}